odoo8_addon_l10n_et_toponym-8.0.1.0.0-py2.7-nspkg.pth
odoo_addons/l10n_et_toponym/__openerp__.py
odoo_addons/l10n_et_toponym/__init__.py
odoo_addons/l10n_et_toponym/README.rst
odoo_addons/l10n_et_toponym/data/res.country.state.csv
odoo_addons/l10n_et_toponym/static/src/img/icon.png
odoo8_addon_l10n_et_toponym-8.0.1.0.0.dist-info/top_level.txt
odoo8_addon_l10n_et_toponym-8.0.1.0.0.dist-info/WHEEL
odoo8_addon_l10n_et_toponym-8.0.1.0.0.dist-info/RECORD
odoo8_addon_l10n_et_toponym-8.0.1.0.0.dist-info/metadata.json
odoo8_addon_l10n_et_toponym-8.0.1.0.0.dist-info/DESCRIPTION.rst
odoo8_addon_l10n_et_toponym-8.0.1.0.0.dist-info/METADATA
odoo8_addon_l10n_et_toponym-8.0.1.0.0.dist-info/namespace_packages.txt
